lxml/ElementInclude.py
lxml/__init__.py
lxml/_elementpath.cp311-win_arm64.pyd
lxml/_elementpath.py
lxml/apihelpers.pxi
lxml/builder.cp311-win_arm64.pyd
lxml/builder.py
lxml/classlookup.pxi
lxml/cleanup.pxi
lxml/cssselect.py
lxml/debug.pxi
lxml/docloader.pxi
lxml/doctestcompare.py
lxml/dtd.pxi
lxml/etree.cp311-win_arm64.pyd
lxml/etree.h
lxml/etree.pyx
lxml/etree_api.h
lxml/extensions.pxi
lxml/iterparse.pxi
lxml/lxml.etree.h
lxml/lxml.etree_api.h
lxml/nsclasses.pxi
lxml/objectify.cp311-win_arm64.pyd
lxml/objectify.pyx
lxml/objectpath.pxi
lxml/parser.pxi
lxml/parsertarget.pxi
lxml/proxy.pxi
lxml/public-api.pxi
lxml/pyclasslookup.py
lxml/readonlytree.pxi
lxml/relaxng.pxi
lxml/sax.cp311-win_arm64.pyd
lxml/sax.py
lxml/saxparser.pxi
lxml/schematron.pxi
lxml/serializer.pxi
lxml/usedoctest.py
lxml/xinclude.pxi
lxml/xmlerror.pxi
lxml/xmlid.pxi
lxml/xmlschema.pxi
lxml/xpath.pxi
lxml/xslt.pxi
lxml/xsltext.pxi
lxml/html/ElementSoup.py
lxml/html/__init__.py
lxml/html/_diffcommand.py
lxml/html/_difflib.cp311-win_arm64.pyd
lxml/html/_difflib.py
lxml/html/_html5builder.py
lxml/html/_setmixin.py
lxml/html/builder.py
lxml/html/clean.py
lxml/html/defs.py
lxml/html/diff.cp311-win_arm64.pyd
lxml/html/diff.py
lxml/html/formfill.py
lxml/html/html5parser.py
lxml/html/soupparser.py
lxml/html/usedoctest.py
lxml/includes/__init__.pxd
lxml/includes/__init__.py
lxml/includes/c14n.pxd
lxml/includes/config.pxd
lxml/includes/dtdvalid.pxd
lxml/includes/etree_defs.h
lxml/includes/etreepublic.pxd
lxml/includes/htmlparser.pxd
lxml/includes/lxml-version.h
lxml/includes/relaxng.pxd
lxml/includes/schematron.pxd
lxml/includes/tree.pxd
lxml/includes/uri.pxd
lxml/includes/xinclude.pxd
lxml/includes/xmlerror.pxd
lxml/includes/xmlparser.pxd
lxml/includes/xmlschema.pxd
lxml/includes/xpath.pxd
lxml/includes/xslt.pxd
lxml/includes/extlibs/__init__.py
lxml/includes/extlibs/zconf.h
lxml/includes/extlibs/zlib.h
lxml/includes/libexslt/__init__.py
lxml/includes/libexslt/exslt.h
lxml/includes/libexslt/exsltconfig.h
lxml-6.0.2.dist-info/licenses/LICENSE.txt
lxml-6.0.2.dist-info/licenses/LICENSES.txt
lxml-6.0.2.dist-info/METADATA
lxml-6.0.2.dist-info/WHEEL
lxml-6.0.2.dist-info/top_level.txt
lxml-6.0.2.dist-info/RECORD
